olp/__init__.py
olp/backends.py
olp/middleware.py
olp/models.py
olp/utils.py
olp-0.3.0.dist-info/METADATA
olp-0.3.0.dist-info/RECORD
olp-0.3.0.dist-info/WHEEL
olp-0.3.0.dist-info/top_level.txt
olp-0.3.0.dist-info/zip-safe
