Metadata-Version: 2.1
Name: olp
Version: 0.3.0
Summary: Object-level permissions across multiple models for Django.
Home-page: https://github.com/Rediker-Software/olp
Author: Kevin Brown
Author-email: kbrown@rediker.com
License: MIT
Platform: UNKNOWN
Classifier: Development Status :: 3 - Alpha
Classifier: Environment :: Web Environment
Classifier: Framework :: Django
Classifier: Intended Audience :: Developers
Classifier: License :: OSI Approved :: MIT License
Classifier: Programming Language :: Python
Classifier: Programming Language :: Python :: 2.7
Classifier: Programming Language :: Python :: 3.4
Requires-Dist: Django (>=1.3)
